{
  "apilist": [
    "das_core",
    "fileReplicas4dataset",
    "files_via_dataset"
  ],
  "ctime": 0.049210071563699997,
  "data": [
    {
      "_id": "58e1fa31f4e31319e05f7d20",
      "cache_id": [
        "58e1fa31f4e31319e05f7d0e",
        "58e1fa31f4e31319e05f7d0c"
      ],
      "das": {
        "api": [
          "fileReplicas4dataset",
          "files_via_dataset"
        ],
        "condition_keys": [
          "dataset.name"
        ],
        "expire": 1491204957,
        "instance": "prod/global",
        "primary_key": "file.name",
        "record": 1,
        "services": [
          {
            "phedex": [
              "phedex"
            ]
          },
          {
            "dbs3": [
              "dbs3"
            ]
          }
        ],
        "system": [
          "phedex",
          "dbs3"
        ],
        "ts": 1491204657.788759
      },
      "das_id": [
        "58e1fa31f4e31319e05f7cf1",
        "58e1fa31f4e31319e05f7cf4"
      ],
      "file": [
        {
          "name": "/store/relval/CMSSW_9_0_0_pre4/RelValSingleGammaPt35_UP15/GEN-SIM/90X_mcRun2_asymptotic_v1-v1/10000/028B8E7F-6EEA-E611-883B-0025905B85D0.root"
        },
        {
          "name": "/store/relval/CMSSW_9_0_0_pre4/RelValSingleGammaPt35_UP15/GEN-SIM/90X_mcRun2_asymptotic_v1-v1/10000/028B8E7F-6EEA-E611-883B-0025905B85D0.root"
        }
      ],
      "qhash": "23b669a5bd415109dc49965a42beaef6"
    },
    {
      "_id": "58e1fa31f4e31319e05f7d1f",
      "cache_id": [
        "58e1fa31f4e31319e05f7d0f",
        "58e1fa31f4e31319e05f7d0b"
      ],
      "das": {
        "api": [
          "fileReplicas4dataset",
          "files_via_dataset"
        ],
        "condition_keys": [
          "dataset.name"
        ],
        "expire": 1491204957,
        "instance": "prod/global",
        "primary_key": "file.name",
        "record": 1,
        "services": [
          {
            "phedex": [
              "phedex"
            ]
          },
          {
            "dbs3": [
              "dbs3"
            ]
          }
        ],
        "system": [
          "phedex",
          "dbs3"
        ],
        "ts": 1491204657.788759
      },
      "das_id": [
        "58e1fa31f4e31319e05f7cf1",
        "58e1fa31f4e31319e05f7cf4"
      ],
      "file": [
        {
          "name": "/store/relval/CMSSW_9_0_0_pre4/RelValSingleGammaPt35_UP15/GEN-SIM/90X_mcRun2_asymptotic_v1-v1/10000/4819E879-6EEA-E611-8EA5-0CC47A4C8E14.root"
        },
        {
          "name": "/store/relval/CMSSW_9_0_0_pre4/RelValSingleGammaPt35_UP15/GEN-SIM/90X_mcRun2_asymptotic_v1-v1/10000/4819E879-6EEA-E611-8EA5-0CC47A4C8E14.root"
        }
      ],
      "qhash": "23b669a5bd415109dc49965a42beaef6"
    }
  ],
  "incache": true,
  "mongo_query": {
    "fields": [
      "file"
    ],
    "filters": {
      "grep": [
        "file.name"
      ],
      "sort": [],
      "unique": 1
    },
    "instance": "prod/global",
    "qcache": 0,
    "spec": {
      "dataset.name": "/RelValSingleGammaPt35_UP15/CMSSW_9_0_0_pre4-90X_mcRun2_asymptotic_v1-v1/GEN-SIM"
    }
  },
  "nresults": 2,
  "status": "ok",
  "timestamp": 1491204658.02
}